tcc_ext/__init__.py
tcc_ext/credentials.py
tencent_sdk_python_ext-0.1.0.dist-info/LICENSE
tencent_sdk_python_ext-0.1.0.dist-info/METADATA
tencent_sdk_python_ext-0.1.0.dist-info/WHEEL
tencent_sdk_python_ext-0.1.0.dist-info/RECORD
