Metadata-Version: 2.1
Name: tencent-sdk-python-ext
Version: 0.1.0
Summary: 腾讯云Python Sdk 插件
Home-page: https://github.com/mingyugg/tencent-sdk-python-ext
Author: thomas
Author-email: thomas.mingyu.guo@gmail.com
Requires-Python: >=3.10,<4.0
Classifier: Programming Language :: Python :: 3
Classifier: Programming Language :: Python :: 3.10
Classifier: Programming Language :: Python :: 3.11
Requires-Dist: tencentcloud-sdk-python-common (>=3.0.1023,<4.0.0)
Project-URL: Repository, https://github.com/mingyugg/tencent-sdk-python-ext
